saunadge/__init__.py
saunadge/server.py
saunadge-0.2.1.dist-info/entry_points.txt
saunadge-0.2.1.dist-info/WHEEL
saunadge-0.2.1.dist-info/METADATA
saunadge-0.2.1.dist-info/RECORD
